mesa/__init__.py
mesa/agent.py
mesa/batchrunner.py
mesa/datacollection.py
mesa/mesa_logging.py
mesa/model.py
mesa/space.py
mesa/discrete_space/__init__.py
mesa/discrete_space/cell.py
mesa/discrete_space/cell_agent.py
mesa/discrete_space/cell_collection.py
mesa/discrete_space/discrete_space.py
mesa/discrete_space/grid.py
mesa/discrete_space/network.py
mesa/discrete_space/property_layer.py
mesa/discrete_space/voronoi.py
mesa/examples/README.md
mesa/examples/__init__.py
mesa/examples/advanced/__init__.py
mesa/examples/advanced/alliance_formation/Readme.md
mesa/examples/advanced/alliance_formation/__init__ .py
mesa/examples/advanced/alliance_formation/agents.py
mesa/examples/advanced/alliance_formation/app.py
mesa/examples/advanced/alliance_formation/model.py
mesa/examples/advanced/epstein_civil_violence/Epstein Civil Violence.ipynb
mesa/examples/advanced/epstein_civil_violence/Readme.md
mesa/examples/advanced/epstein_civil_violence/__init__.py
mesa/examples/advanced/epstein_civil_violence/agents.py
mesa/examples/advanced/epstein_civil_violence/app.py
mesa/examples/advanced/epstein_civil_violence/model.py
mesa/examples/advanced/pd_grid/Readme.md
mesa/examples/advanced/pd_grid/__init__.py
mesa/examples/advanced/pd_grid/agents.py
mesa/examples/advanced/pd_grid/analysis.ipynb
mesa/examples/advanced/pd_grid/app.py
mesa/examples/advanced/pd_grid/model.py
mesa/examples/advanced/sugarscape_g1mt/Readme.md
mesa/examples/advanced/sugarscape_g1mt/__init__.py
mesa/examples/advanced/sugarscape_g1mt/agents.py
mesa/examples/advanced/sugarscape_g1mt/app.py
mesa/examples/advanced/sugarscape_g1mt/model.py
mesa/examples/advanced/sugarscape_g1mt/sugar-map.txt
mesa/examples/advanced/wolf_sheep/Readme.md
mesa/examples/advanced/wolf_sheep/__init__.py
mesa/examples/advanced/wolf_sheep/agents.py
mesa/examples/advanced/wolf_sheep/app.py
mesa/examples/advanced/wolf_sheep/model.py
mesa/examples/basic/__init__.py
mesa/examples/basic/boid_flockers/Readme.md
mesa-3.4.1.dist-info/METADATA
mesa-3.4.1.dist-info/WHEEL
mesa-3.4.1.dist-info/licenses/LICENSE
mesa-3.4.1.dist-info/licenses/NOTICE
mesa-3.4.1.dist-info/RECORD
