Metadata-Version: 2.4
Name: Mesa
Version: 3.4.1
Summary: Agent-based modeling (ABM) in Python
Project-URL: homepage, https://github.com/mesa/mesa
Project-URL: repository, https://github.com/mesa/mesa
Author-email: Mesa Team <maintainers@projectmesa.dev>
License: Apache 2.0
License-File: LICENSE
License-File: NOTICE
Keywords: ABM,agent,based,model,modeling,multi-agent,simulation
Classifier: Development Status :: 3 - Alpha
Classifier: Intended Audience :: Science/Research
Classifier: License :: OSI Approved :: Apache Software License
Classifier: Natural Language :: English
Classifier: Operating System :: OS Independent
Classifier: Programming Language :: Python :: 3 :: Only
Classifier: Programming Language :: Python :: 3.12
Classifier: Programming Language :: Python :: 3.13
Classifier: Programming Language :: Python :: 3.14
Classifier: Topic :: Scientific/Engineering
Classifier: Topic :: Scientific/Engineering :: Artificial Intelligence
Classifier: Topic :: Scientific/Engineering :: Artificial Life
Requires-Python: >=3.12
Requires-Dist: numpy
Requires-Dist: pandas
Requires-Dist: pythran>=0.17.0; sys_platform == 'darwin'
Requires-Dist: scipy
Requires-Dist: tqdm
Provides-Extra: all
Requires-Dist: altair; extra == 'all'
Requires-Dist: ipython; extra == 'all'
Requires-Dist: ipython>=9.2.0; extra == 'all'
Requires-Dist: matplotlib; extra == 'all'
Requires-Dist: myst-nb; extra == 'all'
Requires-Dist: myst-parser; extra == 'all'
Requires-Dist: networkx; extra == 'all'
Requires-Dist: playwright; extra == 'all'
Requires-Dist: pydata-sphinx-theme; extra == 'all'
Requires-Dist: pytest; extra == 'all'
Requires-Dist: pytest-cov; extra == 'all'
Requires-Dist: pytest-ipywidgets; extra == 'all'
Requires-Dist: pytest-mock; extra == 'all'
Requires-Dist: pytest-playwright; extra == 'all'
Requires-Dist: ruff; extra == 'all'
Requires-Dist: scipy; extra == 'all'
Requires-Dist: seaborn; extra == 'all'
Requires-Dist: solara; extra == 'all'
Requires-Dist: sphinx; extra == 'all'
Requires-Dist: sphinx-copybutton; extra == 'all'
Provides-Extra: dev
Requires-Dist: altair; extra == 'dev'
Requires-Dist: ipython>=9.2.0; extra == 'dev'
Requires-Dist: matplotlib; extra == 'dev'
Requires-Dist: networkx; extra == 'dev'
Requires-Dist: playwright; extra == 'dev'
Requires-Dist: pytest; extra == 'dev'
Requires-Dist: pytest-cov; extra == 'dev'
Requires-Dist: pytest-ipywidgets; extra == 'dev'
Requires-Dist: pytest-mock; extra == 'dev'
Requires-Dist: pytest-playwright; extra == 'dev'
Requires-Dist: ruff; extra == 'dev'
Requires-Dist: solara; extra == 'dev'
Requires-Dist: sphinx; extra == 'dev'
Provides-Extra: docs
Requires-Dist: altair; extra == 'docs'
Requires-Dist: ipython; extra == 'docs'
Requires-Dist: matplotlib; extra == 'docs'
Requires-Dist: myst-nb; extra == 'docs'
Requires-Dist: myst-parser; extra == 'docs'
Requires-Dist: networkx; extra == 'docs'
Requires-Dist: pydata-sphinx-theme; extra == 'docs'
Requires-Dist: seaborn; extra == 'docs'
Requires-Dist: solara; extra == 'docs'
Requires-Dist: sphinx; extra == 'docs'
Requires-Dist: sphinx-copybutton; extra == 'docs'
Provides-Extra: examples
Requires-Dist: altair; extra == 'examples'
Requires-Dist: matplotlib; extra == 'examples'
Requires-Dist: networkx; extra == 'examples'
Requires-Dist: pytest; extra == 'examples'
Requires-Dist: scipy; extra == 'examples'
Requires-Dist: solara; extra == 'examples'
Provides-Extra: network
Requires-Dist: networkx; extra == 'network'
Provides-Extra: rec
Requires-Dist: altair; extra == 'rec'
Requires-Dist: matplotlib; extra == 'rec'
Requires-Dist: networkx; extra == 'rec'
Requires-Dist: solara; extra == 'rec'
Provides-Extra: viz
Requires-Dist: altair; extra == 'viz'
Requires-Dist: matplotlib; extra == 'viz'
Requires-Dist: solara; extra == 'viz'
